stackUI/__init__.py
stackUI-0.0.1.dist-info/LICENCE
stackUI-0.0.1.dist-info/METADATA
stackUI-0.0.1.dist-info/WHEEL
stackUI-0.0.1.dist-info/top_level.txt
stackUI-0.0.1.dist-info/RECORD
