Metadata-Version: 2.1
Name: stackUI
Version: 0.0.1
Summary: A python GUI libraray using OpenGL and GLFW
Author-email: janschubrt <jan.schubert0604@gmail.com>
Project-URL: Github, https://github.com/janschubrt/stackUI
Classifier: Programming Language :: Python :: 3
Classifier: License :: OSI Approved :: MIT License
Classifier: Operating System :: Microsoft :: Windows :: Windows 11
Requires-Python: >=3.11.2
License-File: LICENCE
